README.md
setup.py
svart/__init__.py
svart/__main__.py
svart/svart.py
svart.egg-info/PKG-INFO
svart.egg-info/SOURCES.txt
svart.egg-info/dependency_links.txt
svart.egg-info/entry_points.txt
svart.egg-info/requires.txt
svart.egg-info/top_level.txt