Metadata-Version: 2.1
Name: svart
Version: 1.0.0
Summary: Change between dark/light mode depending on the ambient light intensity
Home-page: https://github.com/sdushantha/svart
Author: Siddharth Dushantha
Author-email: siddharth.dushantha@gmail.com
License: UNKNOWN
Platform: UNKNOWN
